MANIFEST.in
README.rst
setup.py
PyVCF.egg-info/PKG-INFO
PyVCF.egg-info/SOURCES.txt
PyVCF.egg-info/dependency_links.txt
PyVCF.egg-info/entry_points.txt
PyVCF.egg-info/requires.txt
PyVCF.egg-info/top_level.txt
scripts/vcf_filter.py
scripts/vcf_melt
vcf/__init__.py
vcf/cparse.pyx
vcf/filters.py
vcf/model.py
vcf/parser.py
vcf/utils.py
vcf/test/__init__.py
vcf/test/prof.py
vcf/test/test_vcf.py