Metadata-Version: 1.1
Name: PyVCF
Version: 0.6.7
Summary: Variant Call Format (VCF) parser for Python
Home-page: https://github.com/jamescasbon/PyVCF
Author: James Casbon and @jdoughertyii
Author-email: casbon@gmail.com
License: UNKNOWN
Keywords: bioinformatics
Platform: UNKNOWN
Classifier: Development Status :: 4 - Beta
Classifier: Intended Audience :: Developers
Classifier: Intended Audience :: Science/Research
Classifier: Operating System :: OS Independent
Classifier: Programming Language :: Python
Classifier: Programming Language :: Python :: 3
Classifier: Topic :: Scientific/Engineering
